tamp/__init__.py
tamp/__init__.pyi
tamp/__main__.py
tamp/_c_common.cpython-313-aarch64-linux-musl.so
tamp/_c_common.pxd
tamp/_c_common.pyx
tamp/_c_compressor.cpython-313-aarch64-linux-musl.so
tamp/_c_compressor.pyx
tamp/_c_decompressor.cpython-313-aarch64-linux-musl.so
tamp/_c_decompressor.pyx
tamp/compressor.py
tamp/compressor_viper.py
tamp/ctamp.pxd
tamp/decompressor.py
tamp/decompressor_viper.py
tamp/py.typed
tamp/_c_src/tamp/common.c
tamp/_c_src/tamp/common.h
tamp/_c_src/tamp/compressor.c
tamp/_c_src/tamp/compressor.h
tamp/_c_src/tamp/compressor_find_match_desktop.c
tamp/_c_src/tamp/decompressor.c
tamp/_c_src/tamp/decompressor.h
tamp/cli/__init__.py
tamp/cli/main.py
tamp-1.11.1.dist-info/LICENSE
tamp-1.11.1.dist-info/METADATA
tamp-1.11.1.dist-info/WHEEL
tamp-1.11.1.dist-info/entry_points.txt
tamp-1.11.1.dist-info/RECORD
