Metadata-Version: 2.1
Name: tamp
Version: 1.11.1
Summary: 
Home-page: https://github.com/BrianPugh/tamp
License: Apache-2.0
Author: Brian Pugh
Requires-Python: >=3.9,<4.0
Classifier: License :: OSI Approved :: Apache Software License
Classifier: Programming Language :: Python :: 3
Classifier: Programming Language :: Python :: 3.9
Classifier: Programming Language :: Python :: 3.10
Classifier: Programming Language :: Python :: 3.11
Classifier: Programming Language :: Python :: 3.12
Classifier: Programming Language :: Python :: 3.13
Requires-Dist: cyclopts (>=1.0.0)
Project-URL: Repository, https://github.com/BrianPugh/tamp
